pgagent_yaml/__init__.py
pgagent_yaml/data_mapping.py
pgagent_yaml/extractor.py
pgagent_yaml/formatter.py
pgagent_yaml/main.py
pgagent_yaml/pg.py
pgagent_yaml/runner.py
pgagent_yaml/statistics.py
pgagent_yaml/str_diff.py
pgagent_yaml/synchronizer.py
pgagent_yaml/models/__init__.py
pgagent_yaml/models/job.py
pgagent_yaml/models/schedule.py
pgagent_yaml/models/step.py
pgagent_yaml-0.4.0.dist-info/licenses/LICENSE
pgagent_yaml-0.4.0.dist-info/METADATA
pgagent_yaml-0.4.0.dist-info/WHEEL
pgagent_yaml-0.4.0.dist-info/entry_points.txt
pgagent_yaml-0.4.0.dist-info/top_level.txt
pgagent_yaml-0.4.0.dist-info/RECORD
