Metadata-Version: 2.4
Name: pgagent-yaml
Version: 0.4.0
Summary: Yaml interface for pgagent
Home-page: https://github.com/andruche/pgagent-yaml
Author: Andrey Chernyakov
License: BSD
Project-URL: Documentation, https://github.com/andruche/pgagent-yaml/blob/master/README.md
Project-URL: Bug Tracker, https://github.com/andruche/pgagent-yaml/issues
Keywords: pgagent,git,yaml
Classifier: Development Status :: 5 - Production/Stable
Classifier: Environment :: Console
Classifier: Operating System :: OS Independent
Classifier: Programming Language :: Python :: 3.9
Classifier: Programming Language :: Python :: 3.10
Classifier: Programming Language :: Python :: 3.11
Classifier: Programming Language :: Python :: 3.12
Classifier: Programming Language :: Python :: 3.13
Requires-Python: >=3.9
License-File: LICENSE
Requires-Dist: pydantic
Requires-Dist: pyyaml
Requires-Dist: asyncpg<0.31.0,>=0.27.0
Dynamic: author
Dynamic: classifier
Dynamic: description
Dynamic: description-content-type
Dynamic: home-page
Dynamic: keywords
Dynamic: license
Dynamic: license-file
Dynamic: project-url
Dynamic: requires-dist
Dynamic: requires-python
Dynamic: summary
